pyqtlet2/__init__.py
pyqtlet2/mapwidget.py
pyqtlet2/leaflet/__init__.py
pyqtlet2/leaflet/control/__init__.py
pyqtlet2/leaflet/control/control.py
pyqtlet2/leaflet/control/draw.py
pyqtlet2/leaflet/control/layers.py
pyqtlet2/leaflet/core/Parser.py
pyqtlet2/leaflet/core/__init__.py
pyqtlet2/leaflet/core/evented.py
pyqtlet2/leaflet/layer/__init__.py
pyqtlet2/leaflet/layer/featuregroup.py
pyqtlet2/leaflet/layer/imageoverlay.py
pyqtlet2/leaflet/layer/layer.py
pyqtlet2/leaflet/layer/layergroup.py
pyqtlet2/leaflet/layer/icon/__init__.py
pyqtlet2/leaflet/layer/icon/icon.py
pyqtlet2/leaflet/layer/marker/__init__.py
pyqtlet2/leaflet/layer/marker/marker.py
pyqtlet2/leaflet/layer/tile/__init__.py
pyqtlet2/leaflet/layer/tile/gridlayer.py
pyqtlet2/leaflet/layer/tile/tilelayer.py
pyqtlet2/leaflet/layer/vector/__init__.py
pyqtlet2/leaflet/layer/vector/circle.py
pyqtlet2/leaflet/layer/vector/circlemarker.py
pyqtlet2/leaflet/layer/vector/path.py
pyqtlet2/leaflet/layer/vector/polygon.py
pyqtlet2/leaflet/layer/vector/polyline.py
pyqtlet2/leaflet/layer/vector/rectangle.py
pyqtlet2/leaflet/map/__init__.py
pyqtlet2/leaflet/map/map.py
pyqtlet2/web/custom.js
pyqtlet2/web/map.html
pyqtlet2/web/modules/leaflet_193/leaflet.css
pyqtlet2/web/modules/leaflet_193/leaflet.js
pyqtlet2/web/modules/leaflet_193/images/layers-2x.png
pyqtlet2/web/modules/leaflet_193/images/layers.png
pyqtlet2/web/modules/leaflet_193/images/marker-icon-2x.png
pyqtlet2/web/modules/leaflet_193/images/marker-icon.png
pyqtlet2/web/modules/leaflet_193/images/marker-shadow.png
pyqtlet2/web/modules/leaflet_draw_414/LICENSE
pyqtlet2/web/modules/leaflet_draw_414/leaflet.draw.css
pyqtlet2/web/modules/leaflet_draw_414/leaflet.draw.js
pyqtlet2/web/modules/leaflet_draw_414/images/layers-2x.png
pyqtlet2/web/modules/leaflet_draw_414/images/layers.png
pyqtlet2/web/modules/leaflet_draw_414/images/marker-icon-2x.png
pyqtlet2/web/modules/leaflet_draw_414/images/marker-icon.png
pyqtlet2/web/modules/leaflet_draw_414/images/marker-shadow.png
pyqtlet2-0.9.3.dist-info/LICENSE.txt
pyqtlet2-0.9.3.dist-info/METADATA
pyqtlet2-0.9.3.dist-info/WHEEL
pyqtlet2-0.9.3.dist-info/top_level.txt
pyqtlet2-0.9.3.dist-info/RECORD
