Metadata-Version: 2.1
Name: pyqtlet2
Version: 0.9.3
Summary: Bringing leaflet maps to Python Qt bindings
Home-page: https://github.com/JaWeilBaum/pyqtlet2
Author: Leon Friedmann
Author-email: leon.friedmann@tum.de
Keywords: leaflet,qtpy,maps,python,python3
License-File: LICENSE.txt
Requires-Dist: QtPy (>=2.0.1)
Provides-Extra: pyqt5
Requires-Dist: PyQt5 (>=5.15.5) ; extra == 'pyqt5'
Requires-Dist: PyQtWebEngine (>=5.15.5) ; extra == 'pyqt5'
Provides-Extra: pyqt6
Requires-Dist: PyQt6 (>=6.2.0) ; extra == 'pyqt6'
Requires-Dist: PyQt6-WebEngine (>=6.2.0) ; extra == 'pyqt6'
Provides-Extra: pyside2
Requires-Dist: PySide2 ; extra == 'pyside2'
Provides-Extra: pyside6
Requires-Dist: PySide6 ; extra == 'pyside6'
